README.rst
setup.cfg
setup.py
async_rpc/__init__.py
async_rpc/serverproxy.py
async_rpc/version.py
async_rpc/xmlrpc.py
async_rpc.egg-info/PKG-INFO
async_rpc.egg-info/SOURCES.txt
async_rpc.egg-info/dependency_links.txt
async_rpc.egg-info/requires.txt
async_rpc.egg-info/top_level.txt
async_rpc.egg-info/zip-safe