Metadata-Version: 2.1
Name: async-rpc
Version: 1.0.0
Summary: Non-blocking XML-RPC client for Python
Home-page: https://github.com/seifert/async-rpc
Author: Jan Seifert
Author-email: jan.seifert@fotkyzcest.net
License: BSD
Platform: any
Classifier: Programming Language :: Python :: 3.5
Classifier: Programming Language :: Python :: 3.6
Classifier: Programming Language :: Python :: 3.7
Classifier: Programming Language :: Python :: 3.8
Classifier: License :: OSI Approved :: BSD License
Classifier: Operating System :: OS Independent
Classifier: Development Status :: 3 - Alpha
